gui_library/.secrets.toml
gui_library/DataFrameViewer.py
gui_library/StatusBar.py
gui_library/__app_name__.py
gui_library/__init__.py
gui_library/__version__.py
gui_library/app_logging.py
gui_library/config.py
gui_library/decorators.py
gui_library/info.py
gui_library/library.py
gui_library/load_gui.py
gui_library/logging_configuration.json
gui_library/settings.toml
gui_library-0.1.0.dist-info/METADATA
gui_library-0.1.0.dist-info/WHEEL
gui_library-0.1.0.dist-info/entry_points.txt
gui_library-0.1.0.dist-info/RECORD
