Metadata-Version: 2.4
Name: gui_library
Version: 0.1.0
Summary: 
Author: dbruce-ae05
Author-email: dbruce.ae05@gmail.com
Requires-Python: >=3.13, <3.15
Classifier: Programming Language :: Python :: 3
Classifier: Programming Language :: Python :: 3.13
Classifier: Programming Language :: Python :: 3.14
Requires-Dist: dynaconf (>=3.2.12,<4.0.0)
